myproject/__init__.py
myproject/models.py
myproject/tests.py
myproject/views.py
pyramid_excel/__init__.py
pyramid_excel-0.0.5.dist-info/DESCRIPTION.rst
pyramid_excel-0.0.5.dist-info/METADATA
pyramid_excel-0.0.5.dist-info/RECORD
pyramid_excel-0.0.5.dist-info/WHEEL
pyramid_excel-0.0.5.dist-info/metadata.json
pyramid_excel-0.0.5.dist-info/top_level.txt
