Metadata-Version: 2.0
Name: pyramid-excel
Version: 0.0.5
Summary: A pyramid extension that provides one application programming interface to read and write data in different excel file formats
Home-page: https://github.com/pyexcel/pyramid-excel
Author: C.W.
Author-email: wangc_2011@hotmail.com
License: New BSD
Download-URL: https://github.com/pyexcel/pyramid-excel/archive/0.0.5.tar.gz
Keywords: API,Pyramid,xls,xlsx,ods,csvpython
Platform: UNKNOWN
Classifier: Topic :: Office/Business
Classifier: Topic :: Utilities
Classifier: Topic :: Software Development :: Libraries
Classifier: Programming Language :: Python
Classifier: License :: OSI Approved :: BSD License
Classifier: Intended Audience :: Developers
Classifier: Programming Language :: Python :: 2.6
Classifier: Programming Language :: Python :: 2.7
Classifier: Programming Language :: Python :: 3.3
Classifier: Programming Language :: Python :: 3.4
Classifier: Programming Language :: Python :: 3.5
Classifier: Programming Language :: Python :: 3.6
Classifier: Development Status :: 3 - Alpha
Classifier: Environment :: Web Environment
Classifier: Topic :: Internet :: WWW/HTTP
Classifier: Topic :: Software Development :: Libraries :: Python Modules
Classifier: Programming Language :: Python :: 2
Classifier: Programming Language :: Python :: 2.7
Classifier: Programming Language :: Python :: 3
Classifier: Programming Language :: Python :: 3.3
Classifier: Programming Language :: Python :: 3.4
Classifier: Programming Language :: Python :: 3.5
Requires-Dist: pyexcel (>=0.5.1.1)
Requires-Dist: pyexcel-webio (>=0.1.2)
Requires-Dist: Pyramid (>=1.4.9)
Provides-Extra: ods
Requires-Dist: pyexcel-ods3 (>=0.4.0); extra == 'ods'
Provides-Extra: xls
Requires-Dist: pyexcel-xls (>=0.4.0); extra == 'xls'
Provides-Extra: xlsx
Requires-Dist: pyexcel-xlsx (>=0.4.0); extra == 'xlsx'
